ataraxis_base_utilities/__init__.py
ataraxis_base_utilities/py.typed
ataraxis_base_utilities/console/__init__.py
ataraxis_base_utilities/console/console_class.py
ataraxis_base_utilities/standalone_methods/__init__.py
ataraxis_base_utilities/standalone_methods/standalone_methods.py
ataraxis_base_utilities-5.1.0.dist-info/METADATA
ataraxis_base_utilities-5.1.0.dist-info/WHEEL
ataraxis_base_utilities-5.1.0.dist-info/licenses/LICENSE
ataraxis_base_utilities-5.1.0.dist-info/RECORD
