Metadata-Version: 2.4
Name: ataraxis-base-utilities
Version: 5.1.0
Summary: A Python library that provides shared utility assets used to support most other Sun (NeuroAI) lab projects.
Project-URL: Homepage, https://github.com/Sun-Lab-NBB/ataraxis-base-utilities
Project-URL: Documentation, https://ataraxis-base-utilities-api-docs.netlify.app/
Author: Ivan Kondratyev
Maintainer-email: Ivan Kondratyev <ik278@cornell.edu>
License:                     GNU GENERAL PUBLIC LICENSE
License-File: LICENSE
Keywords: ataraxis,console,logging,utilities,utility-classes
Classifier: Development Status :: 5 - Production/Stable
Classifier: Intended Audience :: Developers
Classifier: License :: OSI Approved :: GNU General Public License v3 or later (GPLv3+)
Classifier: Operating System :: MacOS :: MacOS X
Classifier: Operating System :: Microsoft :: Windows
Classifier: Operating System :: POSIX :: Linux
Classifier: Programming Language :: Python :: 3.12
Classifier: Programming Language :: Python :: 3.13
Classifier: Programming Language :: Python :: 3.14
Classifier: Topic :: Software Development
Classifier: Typing :: Typed
Requires-Python: <3.15,>=3.12
Requires-Dist: loguru<1,>=0
Requires-Dist: numpy<3,>=2
Provides-Extra: dev
Requires-Dist: ataraxis-automation<8,>=7; extra == 'dev'
Requires-Dist: tox-uv<2,>=1; extra == 'dev'
Requires-Dist: tox<5,>=4; extra == 'dev'
Requires-Dist: uv<1,>=0; extra == 'dev'
